tfmplus/__init__.py
tfmplus/docs/How to install Benewake TF series on PixHawk.pdf
tfmplus/docs/TFmini-Plus-01 A05_Datasheet.pdf
tfmplus/docs/TFmini-Plus-T-01 A04_Product Manual.pdf
tfmplus/docs/__init__.py
tfmplus/docs/TFMini-S/SJ-GU-TFmini-S-01 A00 Datasheet.pdf
tfmplus/docs/TFMini-S/SJ-PM-TFmini-S A00 Product Mannual_EN.pdf
tfmplus/docs/TFMini-S/__init__.py
tfmplus/docs/TI OPT3101/TI_opt3101_datasheet.pdf
tfmplus/docs/TI OPT3101/TI_opt3101_eval module.pdf
tfmplus/docs/TI OPT3101/TI_opt3101_systerm design.pdf
tfmplus/docs/TI OPT3101/__init__.py
tfmplus/tests/__init__.py
tfmplus/tests/tfmp_test.py
tfmplus_budryerson-0.0.15.dist-info/LICENSE
tfmplus_budryerson-0.0.15.dist-info/METADATA
tfmplus_budryerson-0.0.15.dist-info/WHEEL
tfmplus_budryerson-0.0.15.dist-info/top_level.txt
tfmplus_budryerson-0.0.15.dist-info/RECORD
