Metadata-Version: 2.1
Name: tfmplus-budryerson
Version: 0.0.15
Summary: After 14 versions on TestPyPI
Home-page: https://github.com/budryerson/TFMini-Plus_python
Author: Bud Ryerson
Author-email: bud@budryerson.com
License: UNKNOWN
Project-URL: Bug Tracker, https://github.com/budryerson/TFMini-Plus_python/issues
Platform: UNKNOWN
Classifier: Programming Language :: Python :: 3
Classifier: License :: OSI Approved :: MIT License
Classifier: Operating System :: OS Independent
Requires-Python: >=3.6
Requires-Dist: pyserial
